univrm_main/__init__.py
univrm_main/univrm.py
univrm-0.0.1.dist-info/LICENSE
univrm-0.0.1.dist-info/METADATA
univrm-0.0.1.dist-info/WHEEL
univrm-0.0.1.dist-info/entry_points.txt
univrm-0.0.1.dist-info/top_level.txt
univrm-0.0.1.dist-info/RECORD
